odoo/addons/ssi_batch_project_assignment_operating_unit/README.rst
odoo/addons/ssi_batch_project_assignment_operating_unit/__init__.py
odoo/addons/ssi_batch_project_assignment_operating_unit/__manifest__.py
odoo/addons/ssi_batch_project_assignment_operating_unit/i18n/ssi_batch_project_assignment_operating_unit.pot
odoo/addons/ssi_batch_project_assignment_operating_unit/models/__init__.py
odoo/addons/ssi_batch_project_assignment_operating_unit/models/project_batch_assignment.py
odoo/addons/ssi_batch_project_assignment_operating_unit/security/ir_rule/batch_project_assignment.xml
odoo/addons/ssi_batch_project_assignment_operating_unit/security/res_group/batch_project_assignment.xml
odoo/addons/ssi_batch_project_assignment_operating_unit/static/description/icon.png
odoo/addons/ssi_batch_project_assignment_operating_unit/views/batch_project_assignment_views.xml
odoo14_addon_ssi_batch_project_assignment_operating_unit-14.0.1.1.0.dist-info/METADATA
odoo14_addon_ssi_batch_project_assignment_operating_unit-14.0.1.1.0.dist-info/WHEEL
odoo14_addon_ssi_batch_project_assignment_operating_unit-14.0.1.1.0.dist-info/top_level.txt
odoo14_addon_ssi_batch_project_assignment_operating_unit-14.0.1.1.0.dist-info/RECORD
